ALPAFA-0.2.dist-info/DESCRIPTION.rst
ALPAFA-0.2.dist-info/METADATA
ALPAFA-0.2.dist-info/RECORD
ALPAFA-0.2.dist-info/WHEEL
ALPAFA-0.2.dist-info/entry_points.txt
ALPAFA-0.2.dist-info/metadata.json
ALPAFA-0.2.dist-info/top_level.txt
alpafa/__init__.py
alpafa/alpafa.py
alpafa/cli.py
alpafa/parse.py
