Metadata-Version: 2.0
Name: ALPAFA
Version: 0.2
Summary: Algorithm for lexicocentric parameter acquisition by feature assignment
Home-page: https://www.github.com/timothybazalgette/alpafa
Author: Timothy Bazalgette
Author-email: timothy.bazalgette@gmail.com
License: MIT
Keywords: parameters lexicocentrism recos features linguistics
Platform: any
Classifier: Development Status :: 3 - Alpha
Classifier: Environment :: Console
Classifier: Intended Audience :: Science/Research
Classifier: License :: OSI Approved :: MIT License
Classifier: Operating System :: OS Independent
Classifier: Programming Language :: Python :: 3
Classifier: Programming Language :: Python :: 3.3
Classifier: Programming Language :: Python :: 3.4
Classifier: Programming Language :: Python :: 3.5
Classifier: Programming Language :: Python :: 3.6
Requires-Python: >=3
